{"version": 0.6, "generator": "Overpass API 0.7.60.2 e4cf9f7a", "osm3s": {"timestamp_osm_base": "2023-05-09T14:50:24Z", "copyright": "The data included in this document is from www.openstreetmap.org. The data is made available under ODbL."}, "elements": [{"type": "node", "id": 4018874042, "lat": 45.5701698, "lon": -69.5570923}, {"type": "node", "id": 4018874043, "lat": 45.5701717, "lon": -69.5572158}, {"type": "node", "id": 4018874046, "lat": 45.5703046, "lon": -69.5570879}, {"type": "node", "id": 4018874047, "lat": 45.5703065, "lon": -69.5572114}, {"type": "node", "id": 8920691978, "lat": 45.5732095, "lon": -69.5654516, "tags": {"amenity": "toilets"}}, {"type": "node", "id": 8920775089, "lat": 45.5728806, "lon": -69.5670098, "tags": {"amenity": "toilets"}}, {"type": "node", "id": 8920775090, "lat": 45.5719564, "lon": -69.5668816, "tags": {"amenity": "toilets"}}, {"type": "way", "id": 399143543, "nodes": [4018874046, 4018874042, 4018874043, 4018874047, 4018874046], "tags": {"amenity": "toilets", "building": "yes"}}]}